shell_pipeline/__init__.py
shell_pipeline/main.py
shell_pipeline/schema.py
owl_shell_pipeline-0.2.3.dist-info/METADATA
owl_shell_pipeline-0.2.3.dist-info/WHEEL
owl_shell_pipeline-0.2.3.dist-info/entry_points.txt
owl_shell_pipeline-0.2.3.dist-info/top_level.txt
owl_shell_pipeline-0.2.3.dist-info/RECORD
